[
  {
    "id": 1,
    "rol": "presidente",
    "nombre": "fhghjgj",
    "foto": "fotos/junta_presidente_1779070606234.png",
    "partido": "dgh",
    "biografia": "hjgjhj",
    "fecha_inicio": "2026-05-05",
    "fecha_fin": null,
    "updated_at": "2026-05-18T02:16:54.381Z"
  },
  {
    "id": 2,
    "rol": "vicepresidente",
    "nombre": "gfhgh jkh",
    "foto": null,
    "partido": "dgfhgjh",
    "biografia": "fhgj",
    "fecha_inicio": "2026-05-05",
    "fecha_fin": null,
    "updated_at": "2026-05-18T02:16:54.381Z"
  },
  {
    "id": 3,
    "rol": "secretario",
    "nombre": "fhjhjkhk",
    "foto": null,
    "partido": "N/A",
    "biografia": "",
    "fecha_inicio": "2026-05-04",
    "fecha_fin": null,
    "updated_at": "2026-05-18T02:16:54.381Z"
  }
]